README.rst
setup.py
sqlize/__init__.py
sqlize/builder.py
sqlize.egg-info/PKG-INFO
sqlize.egg-info/SOURCES.txt
sqlize.egg-info/dependency_links.txt
sqlize.egg-info/top_level.txt