Metadata-Version: 1.1
Name: sqlize
Version: 1.0
Summary: Lightweight SQL query builder
Home-page: https://github.com/Outernet-project/sqlize
Author: Outernet Inc
Author-email: branko@outernet.is
License: BSD
Keywords: sql query builder
Platform: UNKNOWN
Classifier: Development Status :: 4 - Beta
Classifier: Topic :: Utilities
Classifier: License :: OSI Approved :: GNU General Public License v3 (GPLv3)
Classifier: Programming Language :: Python :: 2.7
Classifier: Programming Language :: Python :: 3.4
